.gitignore
CHANGES.txt
README.rst
setup.cfg
setup.py
tox.ini
churro/__init__.py
churro/collection_wrappers.py
churro/tests.py
churro.egg-info/PKG-INFO
churro.egg-info/SOURCES.txt
churro.egg-info/dependency_links.txt
churro.egg-info/not-zip-safe
churro.egg-info/requires.txt
churro.egg-info/top_level.txt
docs/.gitignore
docs/Makefile
docs/conf.py
docs/index.rst